[
  {
    "name": "vmHHH",
    "category": {
      "name": "kategorija66",
      "coreNumber": 5,
      "RAM": 20,
      "GPUcores": 1
    },
    "nameOrg": "hhhhh",
    "drives": [
      "noviDisk"
    ],
    "activityLog": [],
    "active": "activate"
  },
  {
    "name": "jojojoVM",
    "category": {
      "name": "kategorija123",
      "coreNumber": 42,
      "RAM": 1,
      "GPUcores": 1
    },
    "nameOrg": "ORG1",
    "drives": [
      "HaloDisk"
    ],
    "activityLog": [],
    "active": "activate"
  },
  {
    "name": "novaVMPoslProvera",
    "category": {
      "name": "kategorija225883",
      "coreNumber": 24,
      "RAM": 21,
      "GPUcores": 0
    },
    "nameOrg": "hhhhh",
    "drives": [],
    "activityLog": [],
    "active": "activate"
  },
  {
    "name": "NOVA",
    "category": {
      "name": "kategorija66",
      "coreNumber": 5,
      "RAM": 20,
      "GPUcores": 1
    },
    "nameOrg": "Oracle",
    "drives": [],
    "activityLog": [],
    "active": "activate"
  },
  {
    "name": "WINDOWS10-VM",
    "category": {
      "name": "kategorija123",
      "coreNumber": 42,
      "RAM": 1,
      "GPUcores": 1
    },
    "nameOrg": "Microsoft",
    "drives": [
      "D",
      "F"
    ],
    "activityLog": [
      {
        "start": "Jul 25, 2019 12:00:00 AM",
        "end": "Aug 11, 2019 12:00:00 AM"
      },
      {
        "start": "Jan 23, 2020 12:00:00 AM",
        "end": "Jan 28, 2020 12:00:00 AM"
      }
    ],
    "active": "activate"
  },
  {
    "name": "novaVM",
    "category": {
      "name": "kategorija123",
      "coreNumber": 42,
      "RAM": 1,
      "GPUcores": 1
    },
    "nameOrg": "ORG1",
    "drives": [
      "diskOrg"
    ],
    "activityLog": [],
    "active": "activate"
  },
  {
    "name": "JAFA-HH",
    "category": {
      "name": "kategorija44",
      "coreNumber": 4,
      "RAM": 3,
      "GPUcores": 4
    },
    "nameOrg": "IOS",
    "drives": [],
    "activityLog": [],
    "active": "activate"
  },
  {
    "name": "JAFA",
    "category": {
      "name": "kategorija44",
      "coreNumber": 4,
      "RAM": 3,
      "GPUcores": 4
    },
    "nameOrg": "IOS",
    "drives": [],
    "activityLog": [
      {
        "start": "Jan 29, 2020 2:02:27 PM",
        "end": "Jan 29, 2020 2:02:28 PM"
      },
      {
        "start": "Jan 29, 2020 2:02:29 PM",
        "end": "Jan 29, 2020 2:02:29 PM"
      }
    ],
    "active": "activate"
  },
  {
    "name": "JAVA-VM",
    "category": {
      "name": "kategorija123",
      "coreNumber": 42,
      "RAM": 1,
      "GPUcores": 1
    },
    "nameOrg": "IOS",
    "drives": [
      "C",
      "E"
    ],
    "activityLog": [],
    "active": "activate"
  },
  {
    "name": "ORACLE-VM",
    "category": {
      "name": "kategorija1",
      "coreNumber": 23,
      "RAM": 32,
      "GPUcores": 23
    },
    "nameOrg": "Oracle",
    "drives": [
      "diskOracle"
    ],
    "activityLog": [],
    "active": "activate"
  },
  {
    "name": "vmVmvm",
    "category": {
      "name": "kategorijaNova",
      "coreNumber": 54,
      "RAM": 23,
      "GPUcores": 0
    },
    "nameOrg": "ORG1",
    "drives": [],
    "activityLog": [],
    "active": "activate"
  },
  {
    "name": "VM2",
    "category": {
      "name": "kategorija44",
      "coreNumber": 4,
      "RAM": 3,
      "GPUcores": 4
    },
    "nameOrg": "ORG1",
    "drives": [],
    "activityLog": [],
    "active": "activate"
  },
  {
    "name": "JAFA-mmm",
    "category": {
      "name": "kategorija44",
      "coreNumber": 4,
      "RAM": 3,
      "GPUcores": 4
    },
    "nameOrg": "IOS",
    "drives": [],
    "activityLog": [
      {
        "start": "Jan 8, 2020 12:00:00 AM",
        "end": "Jan 21, 2020 12:00:00 AM"
      },
      {
        "start": "Jan 29, 2020 3:08:36 AM",
        "end": "Jan 29, 2020 3:26:14 AM"
      },
      {
        "start": "Jan 29, 2020 3:29:52 AM"
      }
    ],
    "active": "deactivate"
  }
]